{
  "auth": {
    "user_pool_id": "eu-central-1_0TexbLCkX",
    "aws_region": "eu-central-1",
    "user_pool_client_id": "4m9m8egccm3320h62c2220lh6b",
    "identity_pool_id": "eu-central-1:9bb17dd8-4cac-444e-8d00-ac4e568e7273",
    "mfa_methods": [],
    "standard_required_attributes": [
      "email"
    ],
    "username_attributes": [
      "email"
    ],
    "user_verification_types": [
      "email"
    ],
    "groups": [
      {
        "students": {
          "precedence": 0
        }
      },
      {
        "teachers": {
          "precedence": 1
        }
      },
      {
        "admins": {
          "precedence": 2
        }
      }
    ],
    "mfa_configuration": "NONE",
    "password_policy": {
      "min_length": 8,
      "require_lowercase": true,
      "require_numbers": true,
      "require_symbols": true,
      "require_uppercase": true
    },
    "unauthenticated_identities_enabled": true
  },
  "data": {
    "url": "https://gmqwvcaryfaolfj4swdkg4suya.appsync-api.eu-central-1.amazonaws.com/graphql",
    "aws_region": "eu-central-1",
    "default_authorization_type": "AMAZON_COGNITO_USER_POOLS",
    "authorization_types": [
      "AWS_IAM"
    ],
    "model_introspection": {
      "version": 1,
      "models": {
        "Story": {
          "name": "Story",
          "fields": {
            "id": {
              "name": "id",
              "isArray": false,
              "type": "ID",
              "isRequired": true,
              "attributes": []
            },
            "title": {
              "name": "title",
              "isArray": false,
              "type": "String",
              "isRequired": true,
              "attributes": []
            },
            "content": {
              "name": "content",
              "isArray": false,
              "type": "String",
              "isRequired": true,
              "attributes": []
            },
            "level": {
              "name": "level",
              "isArray": false,
              "type": "String",
              "isRequired": true,
              "attributes": []
            },
            "createdAt": {
              "name": "createdAt",
              "isArray": false,
              "type": "AWSDateTime",
              "isRequired": true,
              "attributes": []
            },
            "studentId": {
              "name": "studentId",
              "isArray": false,
              "type": "ID",
              "isRequired": false,
              "attributes": []
            },
            "student": {
              "name": "student",
              "isArray": false,
              "type": {
                "model": "StudentProfile"
              },
              "isRequired": false,
              "attributes": [],
              "association": {
                "connectionType": "BELONGS_TO",
                "targetNames": [
                  "studentId"
                ]
              }
            },
            "teacherId": {
              "name": "teacherId",
              "isArray": false,
              "type": "ID",
              "isRequired": false,
              "attributes": []
            },
            "teacher": {
              "name": "teacher",
              "isArray": false,
              "type": {
                "model": "TeacherProfile"
              },
              "isRequired": false,
              "attributes": [],
              "association": {
                "connectionType": "BELONGS_TO",
                "targetNames": [
                  "teacherId"
                ]
              }
            },
            "unknownWordIds": {
              "name": "unknownWordIds",
              "isArray": true,
              "type": "String",
              "isRequired": false,
              "attributes": [],
              "isArrayNullable": true
            },
            "highlightedWords": {
              "name": "highlightedWords",
              "isArray": true,
              "type": {
                "nonModel": "HighlightedWord"
              },
              "isRequired": false,
              "attributes": [],
              "isArrayNullable": true
            },
            "mode": {
              "name": "mode",
              "isArray": false,
              "type": {
                "enum": "StoryGenerationMode"
              },
              "isRequired": false,
              "attributes": []
            },
            "updatedAt": {
              "name": "updatedAt",
              "isArray": false,
              "type": "AWSDateTime",
              "isRequired": false,
              "attributes": [],
              "isReadOnly": true
            }
          },
          "syncable": true,
          "pluralName": "Stories",
          "attributes": [
            {
              "type": "model",
              "properties": {}
            },
            {
              "type": "key",
              "properties": {
                "name": "storiesByStudentId",
                "queryField": "listStoryByStudentId",
                "fields": [
                  "studentId"
                ]
              }
            },
            {
              "type": "key",
              "properties": {
                "name": "storiesByTeacherId",
                "queryField": "listStoryByTeacherId",
                "fields": [
                  "teacherId"
                ]
              }
            },
            {
              "type": "auth",
              "properties": {
                "rules": [
                  {
                    "allow": "private",
                    "operations": [
                      "create",
                      "update",
                      "delete",
                      "read"
                    ]
                  }
                ]
              }
            }
          ],
          "primaryKeyInfo": {
            "isCustomPrimaryKey": false,
            "primaryKeyFieldName": "id",
            "sortKeyFieldNames": []
          }
        },
        "Word": {
          "name": "Word",
          "fields": {
            "id": {
              "name": "id",
              "isArray": false,
              "type": "ID",
              "isRequired": true,
              "attributes": []
            },
            "studentId": {
              "name": "studentId",
              "isArray": false,
              "type": "ID",
              "isRequired": true,
              "attributes": []
            },
            "student": {
              "name": "student",
              "isArray": false,
              "type": {
                "model": "StudentProfile"
              },
              "isRequired": false,
              "attributes": [],
              "association": {
                "connectionType": "BELONGS_TO",
                "targetNames": [
                  "studentId"
                ]
              }
            },
            "text": {
              "name": "text",
              "isArray": false,
              "type": "String",
              "isRequired": true,
              "attributes": []
            },
            "translation": {
              "name": "translation",
              "isArray": false,
              "type": "String",
              "isRequired": true,
              "attributes": []
            },
            "exampleSentence": {
              "name": "exampleSentence",
              "isArray": false,
              "type": "String",
              "isRequired": false,
              "attributes": []
            },
            "mastery": {
              "name": "mastery",
              "isArray": false,
              "type": {
                "enum": "WordMastery"
              },
              "isRequired": true,
              "attributes": []
            },
            "lastReviewedAt": {
              "name": "lastReviewedAt",
              "isArray": false,
              "type": "AWSDateTime",
              "isRequired": false,
              "attributes": []
            },
            "createdAt": {
              "name": "createdAt",
              "isArray": false,
              "type": "AWSDateTime",
              "isRequired": false,
              "attributes": [],
              "isReadOnly": true
            },
            "updatedAt": {
              "name": "updatedAt",
              "isArray": false,
              "type": "AWSDateTime",
              "isRequired": false,
              "attributes": [],
              "isReadOnly": true
            }
          },
          "syncable": true,
          "pluralName": "Words",
          "attributes": [
            {
              "type": "model",
              "properties": {}
            },
            {
              "type": "key",
              "properties": {
                "name": "wordsByStudentId",
                "queryField": "listWordByStudentId",
                "fields": [
                  "studentId"
                ]
              }
            },
            {
              "type": "auth",
              "properties": {
                "rules": [
                  {
                    "allow": "private",
                    "operations": [
                      "create",
                      "update",
                      "delete",
                      "read"
                    ]
                  }
                ]
              }
            }
          ],
          "primaryKeyInfo": {
            "isCustomPrimaryKey": false,
            "primaryKeyFieldName": "id",
            "sortKeyFieldNames": []
          }
        },
        "Achievement": {
          "name": "Achievement",
          "fields": {
            "id": {
              "name": "id",
              "isArray": false,
              "type": "ID",
              "isRequired": true,
              "attributes": []
            },
            "studentId": {
              "name": "studentId",
              "isArray": false,
              "type": "ID",
              "isRequired": true,
              "attributes": []
            },
            "student": {
              "name": "student",
              "isArray": false,
              "type": {
                "model": "StudentProfile"
              },
              "isRequired": false,
              "attributes": [],
              "association": {
                "connectionType": "BELONGS_TO",
                "targetNames": [
                  "studentId"
                ]
              }
            },
            "title": {
              "name": "title",
              "isArray": false,
              "type": "String",
              "isRequired": true,
              "attributes": []
            },
            "description": {
              "name": "description",
              "isArray": false,
              "type": "String",
              "isRequired": true,
              "attributes": []
            },
            "icon": {
              "name": "icon",
              "isArray": false,
              "type": "String",
              "isRequired": true,
              "attributes": []
            },
            "achievedAt": {
              "name": "achievedAt",
              "isArray": false,
              "type": "AWSDate",
              "isRequired": true,
              "attributes": []
            },
            "createdAt": {
              "name": "createdAt",
              "isArray": false,
              "type": "AWSDateTime",
              "isRequired": false,
              "attributes": [],
              "isReadOnly": true
            },
            "updatedAt": {
              "name": "updatedAt",
              "isArray": false,
              "type": "AWSDateTime",
              "isRequired": false,
              "attributes": [],
              "isReadOnly": true
            }
          },
          "syncable": true,
          "pluralName": "Achievements",
          "attributes": [
            {
              "type": "model",
              "properties": {}
            },
            {
              "type": "key",
              "properties": {
                "name": "achievementsByStudentId",
                "queryField": "listAchievementByStudentId",
                "fields": [
                  "studentId"
                ]
              }
            },
            {
              "type": "auth",
              "properties": {
                "rules": [
                  {
                    "allow": "private",
                    "operations": [
                      "create",
                      "update",
                      "delete",
                      "read"
                    ]
                  }
                ]
              }
            }
          ],
          "primaryKeyInfo": {
            "isCustomPrimaryKey": false,
            "primaryKeyFieldName": "id",
            "sortKeyFieldNames": []
          }
        },
        "StudentProfile": {
          "name": "StudentProfile",
          "fields": {
            "id": {
              "name": "id",
              "isArray": false,
              "type": "ID",
              "isRequired": true,
              "attributes": []
            },
            "name": {
              "name": "name",
              "isArray": false,
              "type": "String",
              "isRequired": true,
              "attributes": []
            },
            "email": {
              "name": "email",
              "isArray": false,
              "type": "AWSEmail",
              "isRequired": true,
              "attributes": []
            },
            "birthday": {
              "name": "birthday",
              "isArray": false,
              "type": "AWSDate",
              "isRequired": false,
              "attributes": []
            },
            "avatarUrl": {
              "name": "avatarUrl",
              "isArray": false,
              "type": "AWSURL",
              "isRequired": false,
              "attributes": []
            },
            "level": {
              "name": "level",
              "isArray": false,
              "type": "String",
              "isRequired": true,
              "attributes": []
            },
            "streak": {
              "name": "streak",
              "isArray": false,
              "type": "Int",
              "isRequired": true,
              "attributes": []
            },
            "vocabularyCount": {
              "name": "vocabularyCount",
              "isArray": false,
              "type": "Int",
              "isRequired": true,
              "attributes": []
            },
            "words": {
              "name": "words",
              "isArray": true,
              "type": {
                "model": "Word"
              },
              "isRequired": false,
              "attributes": [],
              "isArrayNullable": true,
              "association": {
                "connectionType": "HAS_MANY",
                "associatedWith": [
                  "studentId"
                ]
              }
            },
            "stories": {
              "name": "stories",
              "isArray": true,
              "type": {
                "model": "Story"
              },
              "isRequired": false,
              "attributes": [],
              "isArrayNullable": true,
              "association": {
                "connectionType": "HAS_MANY",
                "associatedWith": [
                  "studentId"
                ]
              }
            },
            "achievements": {
              "name": "achievements",
              "isArray": true,
              "type": {
                "model": "Achievement"
              },
              "isRequired": false,
              "attributes": [],
              "isArrayNullable": true,
              "association": {
                "connectionType": "HAS_MANY",
                "associatedWith": [
                  "studentId"
                ]
              }
            },
            "submissions": {
              "name": "submissions",
              "isArray": true,
              "type": {
                "model": "SubmissionSummary"
              },
              "isRequired": false,
              "attributes": [],
              "isArrayNullable": true,
              "association": {
                "connectionType": "HAS_MANY",
                "associatedWith": [
                  "studentId"
                ]
              }
            },
            "createdAt": {
              "name": "createdAt",
              "isArray": false,
              "type": "AWSDateTime",
              "isRequired": false,
              "attributes": [],
              "isReadOnly": true
            },
            "updatedAt": {
              "name": "updatedAt",
              "isArray": false,
              "type": "AWSDateTime",
              "isRequired": false,
              "attributes": [],
              "isReadOnly": true
            }
          },
          "syncable": true,
          "pluralName": "StudentProfiles",
          "attributes": [
            {
              "type": "model",
              "properties": {}
            },
            {
              "type": "auth",
              "properties": {
                "rules": [
                  {
                    "allow": "private",
                    "operations": [
                      "create",
                      "update",
                      "delete",
                      "read"
                    ]
                  }
                ]
              }
            }
          ],
          "primaryKeyInfo": {
            "isCustomPrimaryKey": false,
            "primaryKeyFieldName": "id",
            "sortKeyFieldNames": []
          }
        },
        "TeacherProfile": {
          "name": "TeacherProfile",
          "fields": {
            "id": {
              "name": "id",
              "isArray": false,
              "type": "ID",
              "isRequired": true,
              "attributes": []
            },
            "name": {
              "name": "name",
              "isArray": false,
              "type": "String",
              "isRequired": true,
              "attributes": []
            },
            "email": {
              "name": "email",
              "isArray": false,
              "type": "AWSEmail",
              "isRequired": true,
              "attributes": []
            },
            "school": {
              "name": "school",
              "isArray": false,
              "type": "String",
              "isRequired": false,
              "attributes": []
            },
            "classes": {
              "name": "classes",
              "isArray": true,
              "type": {
                "model": "ClassSummary"
              },
              "isRequired": false,
              "attributes": [],
              "isArrayNullable": true,
              "association": {
                "connectionType": "HAS_MANY",
                "associatedWith": [
                  "teacherId"
                ]
              }
            },
            "stories": {
              "name": "stories",
              "isArray": true,
              "type": {
                "model": "Story"
              },
              "isRequired": false,
              "attributes": [],
              "isArrayNullable": true,
              "association": {
                "connectionType": "HAS_MANY",
                "associatedWith": [
                  "teacherId"
                ]
              }
            },
            "assignments": {
              "name": "assignments",
              "isArray": true,
              "type": {
                "model": "Assignment"
              },
              "isRequired": false,
              "attributes": [],
              "isArrayNullable": true,
              "association": {
                "connectionType": "HAS_MANY",
                "associatedWith": [
                  "teacherId"
                ]
              }
            },
            "submissions": {
              "name": "submissions",
              "isArray": true,
              "type": {
                "model": "SubmissionSummary"
              },
              "isRequired": false,
              "attributes": [],
              "isArrayNullable": true,
              "association": {
                "connectionType": "HAS_MANY",
                "associatedWith": [
                  "teacherId"
                ]
              }
            },
            "createdAt": {
              "name": "createdAt",
              "isArray": false,
              "type": "AWSDateTime",
              "isRequired": false,
              "attributes": [],
              "isReadOnly": true
            },
            "updatedAt": {
              "name": "updatedAt",
              "isArray": false,
              "type": "AWSDateTime",
              "isRequired": false,
              "attributes": [],
              "isReadOnly": true
            }
          },
          "syncable": true,
          "pluralName": "TeacherProfiles",
          "attributes": [
            {
              "type": "model",
              "properties": {}
            },
            {
              "type": "auth",
              "properties": {
                "rules": [
                  {
                    "allow": "private",
                    "operations": [
                      "create",
                      "update",
                      "delete",
                      "read"
                    ]
                  }
                ]
              }
            }
          ],
          "primaryKeyInfo": {
            "isCustomPrimaryKey": false,
            "primaryKeyFieldName": "id",
            "sortKeyFieldNames": []
          }
        },
        "ClassSummary": {
          "name": "ClassSummary",
          "fields": {
            "id": {
              "name": "id",
              "isArray": false,
              "type": "ID",
              "isRequired": true,
              "attributes": []
            },
            "teacherId": {
              "name": "teacherId",
              "isArray": false,
              "type": "ID",
              "isRequired": true,
              "attributes": []
            },
            "teacher": {
              "name": "teacher",
              "isArray": false,
              "type": {
                "model": "TeacherProfile"
              },
              "isRequired": false,
              "attributes": [],
              "association": {
                "connectionType": "BELONGS_TO",
                "targetNames": [
                  "teacherId"
                ]
              }
            },
            "name": {
              "name": "name",
              "isArray": false,
              "type": "String",
              "isRequired": true,
              "attributes": []
            },
            "studentCount": {
              "name": "studentCount",
              "isArray": false,
              "type": "Int",
              "isRequired": true,
              "attributes": []
            },
            "averageLevel": {
              "name": "averageLevel",
              "isArray": false,
              "type": "String",
              "isRequired": true,
              "attributes": []
            },
            "completionRate": {
              "name": "completionRate",
              "isArray": false,
              "type": "Float",
              "isRequired": true,
              "attributes": []
            },
            "mostChallengingWord": {
              "name": "mostChallengingWord",
              "isArray": false,
              "type": "String",
              "isRequired": false,
              "attributes": []
            },
            "createdAt": {
              "name": "createdAt",
              "isArray": false,
              "type": "AWSDateTime",
              "isRequired": false,
              "attributes": [],
              "isReadOnly": true
            },
            "updatedAt": {
              "name": "updatedAt",
              "isArray": false,
              "type": "AWSDateTime",
              "isRequired": false,
              "attributes": [],
              "isReadOnly": true
            }
          },
          "syncable": true,
          "pluralName": "ClassSummaries",
          "attributes": [
            {
              "type": "model",
              "properties": {}
            },
            {
              "type": "key",
              "properties": {
                "name": "classSummariesByTeacherId",
                "queryField": "listClassSummaryByTeacherId",
                "fields": [
                  "teacherId"
                ]
              }
            },
            {
              "type": "auth",
              "properties": {
                "rules": [
                  {
                    "allow": "private",
                    "operations": [
                      "create",
                      "update",
                      "delete",
                      "read"
                    ]
                  }
                ]
              }
            }
          ],
          "primaryKeyInfo": {
            "isCustomPrimaryKey": false,
            "primaryKeyFieldName": "id",
            "sortKeyFieldNames": []
          }
        },
        "Assignment": {
          "name": "Assignment",
          "fields": {
            "id": {
              "name": "id",
              "isArray": false,
              "type": "ID",
              "isRequired": true,
              "attributes": []
            },
            "teacherId": {
              "name": "teacherId",
              "isArray": false,
              "type": "ID",
              "isRequired": true,
              "attributes": []
            },
            "teacher": {
              "name": "teacher",
              "isArray": false,
              "type": {
                "model": "TeacherProfile"
              },
              "isRequired": false,
              "attributes": [],
              "association": {
                "connectionType": "BELONGS_TO",
                "targetNames": [
                  "teacherId"
                ]
              }
            },
            "title": {
              "name": "title",
              "isArray": false,
              "type": "String",
              "isRequired": true,
              "attributes": []
            },
            "dueDate": {
              "name": "dueDate",
              "isArray": false,
              "type": "AWSDate",
              "isRequired": true,
              "attributes": []
            },
            "level": {
              "name": "level",
              "isArray": false,
              "type": "String",
              "isRequired": true,
              "attributes": []
            },
            "status": {
              "name": "status",
              "isArray": false,
              "type": {
                "enum": "AssignmentStatus"
              },
              "isRequired": true,
              "attributes": []
            },
            "requiredWords": {
              "name": "requiredWords",
              "isArray": true,
              "type": "String",
              "isRequired": false,
              "attributes": [],
              "isArrayNullable": true
            },
            "excludedWords": {
              "name": "excludedWords",
              "isArray": true,
              "type": "String",
              "isRequired": false,
              "attributes": [],
              "isArrayNullable": true
            },
            "createdAt": {
              "name": "createdAt",
              "isArray": false,
              "type": "AWSDateTime",
              "isRequired": true,
              "attributes": []
            },
            "submissions": {
              "name": "submissions",
              "isArray": true,
              "type": {
                "model": "SubmissionSummary"
              },
              "isRequired": false,
              "attributes": [],
              "isArrayNullable": true,
              "association": {
                "connectionType": "HAS_MANY",
                "associatedWith": [
                  "assignmentId"
                ]
              }
            },
            "updatedAt": {
              "name": "updatedAt",
              "isArray": false,
              "type": "AWSDateTime",
              "isRequired": false,
              "attributes": [],
              "isReadOnly": true
            }
          },
          "syncable": true,
          "pluralName": "Assignments",
          "attributes": [
            {
              "type": "model",
              "properties": {}
            },
            {
              "type": "key",
              "properties": {
                "name": "assignmentsByTeacherId",
                "queryField": "listAssignmentByTeacherId",
                "fields": [
                  "teacherId"
                ]
              }
            },
            {
              "type": "auth",
              "properties": {
                "rules": [
                  {
                    "allow": "private",
                    "operations": [
                      "create",
                      "update",
                      "delete",
                      "read"
                    ]
                  }
                ]
              }
            }
          ],
          "primaryKeyInfo": {
            "isCustomPrimaryKey": false,
            "primaryKeyFieldName": "id",
            "sortKeyFieldNames": []
          }
        },
        "SubmissionSummary": {
          "name": "SubmissionSummary",
          "fields": {
            "id": {
              "name": "id",
              "isArray": false,
              "type": "ID",
              "isRequired": true,
              "attributes": []
            },
            "assignmentId": {
              "name": "assignmentId",
              "isArray": false,
              "type": "ID",
              "isRequired": true,
              "attributes": []
            },
            "assignment": {
              "name": "assignment",
              "isArray": false,
              "type": {
                "model": "Assignment"
              },
              "isRequired": false,
              "attributes": [],
              "association": {
                "connectionType": "BELONGS_TO",
                "targetNames": [
                  "assignmentId"
                ]
              }
            },
            "teacherId": {
              "name": "teacherId",
              "isArray": false,
              "type": "ID",
              "isRequired": true,
              "attributes": []
            },
            "teacher": {
              "name": "teacher",
              "isArray": false,
              "type": {
                "model": "TeacherProfile"
              },
              "isRequired": false,
              "attributes": [],
              "association": {
                "connectionType": "BELONGS_TO",
                "targetNames": [
                  "teacherId"
                ]
              }
            },
            "studentId": {
              "name": "studentId",
              "isArray": false,
              "type": "ID",
              "isRequired": true,
              "attributes": []
            },
            "student": {
              "name": "student",
              "isArray": false,
              "type": {
                "model": "StudentProfile"
              },
              "isRequired": false,
              "attributes": [],
              "association": {
                "connectionType": "BELONGS_TO",
                "targetNames": [
                  "studentId"
                ]
              }
            },
            "studentName": {
              "name": "studentName",
              "isArray": false,
              "type": "String",
              "isRequired": true,
              "attributes": []
            },
            "submittedAt": {
              "name": "submittedAt",
              "isArray": false,
              "type": "AWSDateTime",
              "isRequired": true,
              "attributes": []
            },
            "score": {
              "name": "score",
              "isArray": false,
              "type": "Int",
              "isRequired": false,
              "attributes": []
            },
            "unknownWords": {
              "name": "unknownWords",
              "isArray": true,
              "type": "String",
              "isRequired": false,
              "attributes": [],
              "isArrayNullable": false
            },
            "createdAt": {
              "name": "createdAt",
              "isArray": false,
              "type": "AWSDateTime",
              "isRequired": false,
              "attributes": [],
              "isReadOnly": true
            },
            "updatedAt": {
              "name": "updatedAt",
              "isArray": false,
              "type": "AWSDateTime",
              "isRequired": false,
              "attributes": [],
              "isReadOnly": true
            }
          },
          "syncable": true,
          "pluralName": "SubmissionSummaries",
          "attributes": [
            {
              "type": "model",
              "properties": {}
            },
            {
              "type": "key",
              "properties": {
                "name": "submissionSummariesByAssignmentId",
                "queryField": "listSubmissionSummaryByAssignmentId",
                "fields": [
                  "assignmentId"
                ]
              }
            },
            {
              "type": "key",
              "properties": {
                "name": "submissionSummariesByTeacherId",
                "queryField": "listSubmissionSummaryByTeacherId",
                "fields": [
                  "teacherId"
                ]
              }
            },
            {
              "type": "auth",
              "properties": {
                "rules": [
                  {
                    "allow": "private",
                    "operations": [
                      "create",
                      "update",
                      "delete",
                      "read"
                    ]
                  }
                ]
              }
            }
          ],
          "primaryKeyInfo": {
            "isCustomPrimaryKey": false,
            "primaryKeyFieldName": "id",
            "sortKeyFieldNames": []
          }
        }
      },
      "enums": {
        "WordMastery": {
          "name": "WordMastery",
          "values": [
            "known",
            "learning",
            "unknown"
          ]
        },
        "AssignmentStatus": {
          "name": "AssignmentStatus",
          "values": [
            "draft",
            "sent",
            "submitted",
            "graded"
          ]
        },
        "StoryGenerationMode": {
          "name": "StoryGenerationMode",
          "values": [
            "placement",
            "personalized",
            "teacher"
          ]
        }
      },
      "nonModels": {
        "HighlightedWord": {
          "name": "HighlightedWord",
          "fields": {
            "word": {
              "name": "word",
              "isArray": false,
              "type": "String",
              "isRequired": false,
              "attributes": []
            },
            "offset": {
              "name": "offset",
              "isArray": false,
              "type": "Int",
              "isRequired": false,
              "attributes": []
            },
            "length": {
              "name": "length",
              "isArray": false,
              "type": "Int",
              "isRequired": false,
              "attributes": []
            }
          }
        },
        "StoryView": {
          "name": "StoryView",
          "fields": {
            "id": {
              "name": "id",
              "isArray": false,
              "type": "ID",
              "isRequired": true,
              "attributes": []
            },
            "studentId": {
              "name": "studentId",
              "isArray": false,
              "type": "ID",
              "isRequired": false,
              "attributes": []
            },
            "teacherId": {
              "name": "teacherId",
              "isArray": false,
              "type": "ID",
              "isRequired": false,
              "attributes": []
            },
            "title": {
              "name": "title",
              "isArray": false,
              "type": "String",
              "isRequired": true,
              "attributes": []
            },
            "content": {
              "name": "content",
              "isArray": false,
              "type": "String",
              "isRequired": true,
              "attributes": []
            },
            "level": {
              "name": "level",
              "isArray": false,
              "type": "String",
              "isRequired": true,
              "attributes": []
            },
            "createdAt": {
              "name": "createdAt",
              "isArray": false,
              "type": "AWSDateTime",
              "isRequired": true,
              "attributes": []
            },
            "updatedAt": {
              "name": "updatedAt",
              "isArray": false,
              "type": "AWSDateTime",
              "isRequired": true,
              "attributes": []
            },
            "mode": {
              "name": "mode",
              "isArray": false,
              "type": {
                "enum": "StoryGenerationMode"
              },
              "isRequired": false,
              "attributes": []
            },
            "unknownWordIds": {
              "name": "unknownWordIds",
              "isArray": true,
              "type": "String",
              "isRequired": false,
              "attributes": [],
              "isArrayNullable": true
            },
            "highlightedWords": {
              "name": "highlightedWords",
              "isArray": true,
              "type": {
                "nonModel": "HighlightedWord"
              },
              "isRequired": false,
              "attributes": [],
              "isArrayNullable": true
            }
          }
        },
        "WordView": {
          "name": "WordView",
          "fields": {
            "id": {
              "name": "id",
              "isArray": false,
              "type": "ID",
              "isRequired": true,
              "attributes": []
            },
            "studentId": {
              "name": "studentId",
              "isArray": false,
              "type": "ID",
              "isRequired": true,
              "attributes": []
            },
            "text": {
              "name": "text",
              "isArray": false,
              "type": "String",
              "isRequired": true,
              "attributes": []
            },
            "translation": {
              "name": "translation",
              "isArray": false,
              "type": "String",
              "isRequired": true,
              "attributes": []
            },
            "exampleSentence": {
              "name": "exampleSentence",
              "isArray": false,
              "type": "String",
              "isRequired": false,
              "attributes": []
            },
            "mastery": {
              "name": "mastery",
              "isArray": false,
              "type": {
                "enum": "WordMastery"
              },
              "isRequired": true,
              "attributes": []
            },
            "lastReviewedAt": {
              "name": "lastReviewedAt",
              "isArray": false,
              "type": "AWSDateTime",
              "isRequired": false,
              "attributes": []
            },
            "createdAt": {
              "name": "createdAt",
              "isArray": false,
              "type": "AWSDateTime",
              "isRequired": true,
              "attributes": []
            },
            "updatedAt": {
              "name": "updatedAt",
              "isArray": false,
              "type": "AWSDateTime",
              "isRequired": true,
              "attributes": []
            }
          }
        },
        "AchievementView": {
          "name": "AchievementView",
          "fields": {
            "id": {
              "name": "id",
              "isArray": false,
              "type": "ID",
              "isRequired": true,
              "attributes": []
            },
            "studentId": {
              "name": "studentId",
              "isArray": false,
              "type": "ID",
              "isRequired": true,
              "attributes": []
            },
            "title": {
              "name": "title",
              "isArray": false,
              "type": "String",
              "isRequired": true,
              "attributes": []
            },
            "description": {
              "name": "description",
              "isArray": false,
              "type": "String",
              "isRequired": true,
              "attributes": []
            },
            "icon": {
              "name": "icon",
              "isArray": false,
              "type": "String",
              "isRequired": true,
              "attributes": []
            },
            "achievedAt": {
              "name": "achievedAt",
              "isArray": false,
              "type": "AWSDate",
              "isRequired": true,
              "attributes": []
            },
            "createdAt": {
              "name": "createdAt",
              "isArray": false,
              "type": "AWSDateTime",
              "isRequired": true,
              "attributes": []
            },
            "updatedAt": {
              "name": "updatedAt",
              "isArray": false,
              "type": "AWSDateTime",
              "isRequired": true,
              "attributes": []
            }
          }
        },
        "StudentProfileView": {
          "name": "StudentProfileView",
          "fields": {
            "id": {
              "name": "id",
              "isArray": false,
              "type": "ID",
              "isRequired": true,
              "attributes": []
            },
            "name": {
              "name": "name",
              "isArray": false,
              "type": "String",
              "isRequired": true,
              "attributes": []
            },
            "email": {
              "name": "email",
              "isArray": false,
              "type": "AWSEmail",
              "isRequired": true,
              "attributes": []
            },
            "birthday": {
              "name": "birthday",
              "isArray": false,
              "type": "AWSDate",
              "isRequired": false,
              "attributes": []
            },
            "avatarUrl": {
              "name": "avatarUrl",
              "isArray": false,
              "type": "AWSURL",
              "isRequired": false,
              "attributes": []
            },
            "level": {
              "name": "level",
              "isArray": false,
              "type": "String",
              "isRequired": true,
              "attributes": []
            },
            "streak": {
              "name": "streak",
              "isArray": false,
              "type": "Int",
              "isRequired": true,
              "attributes": []
            },
            "vocabularyCount": {
              "name": "vocabularyCount",
              "isArray": false,
              "type": "Int",
              "isRequired": true,
              "attributes": []
            },
            "createdAt": {
              "name": "createdAt",
              "isArray": false,
              "type": "AWSDateTime",
              "isRequired": true,
              "attributes": []
            },
            "updatedAt": {
              "name": "updatedAt",
              "isArray": false,
              "type": "AWSDateTime",
              "isRequired": true,
              "attributes": []
            },
            "achievements": {
              "name": "achievements",
              "isArray": true,
              "type": {
                "nonModel": "AchievementView"
              },
              "isRequired": false,
              "attributes": [],
              "isArrayNullable": true
            },
            "words": {
              "name": "words",
              "isArray": true,
              "type": {
                "nonModel": "WordView"
              },
              "isRequired": false,
              "attributes": [],
              "isArrayNullable": true
            },
            "stories": {
              "name": "stories",
              "isArray": true,
              "type": {
                "nonModel": "StoryView"
              },
              "isRequired": false,
              "attributes": [],
              "isArrayNullable": true
            }
          }
        },
        "TeacherProfileView": {
          "name": "TeacherProfileView",
          "fields": {
            "id": {
              "name": "id",
              "isArray": false,
              "type": "ID",
              "isRequired": true,
              "attributes": []
            },
            "name": {
              "name": "name",
              "isArray": false,
              "type": "String",
              "isRequired": true,
              "attributes": []
            },
            "email": {
              "name": "email",
              "isArray": false,
              "type": "AWSEmail",
              "isRequired": true,
              "attributes": []
            },
            "school": {
              "name": "school",
              "isArray": false,
              "type": "String",
              "isRequired": false,
              "attributes": []
            },
            "createdAt": {
              "name": "createdAt",
              "isArray": false,
              "type": "AWSDateTime",
              "isRequired": true,
              "attributes": []
            },
            "updatedAt": {
              "name": "updatedAt",
              "isArray": false,
              "type": "AWSDateTime",
              "isRequired": true,
              "attributes": []
            }
          }
        },
        "AssignmentView": {
          "name": "AssignmentView",
          "fields": {
            "id": {
              "name": "id",
              "isArray": false,
              "type": "ID",
              "isRequired": true,
              "attributes": []
            },
            "teacherId": {
              "name": "teacherId",
              "isArray": false,
              "type": "ID",
              "isRequired": true,
              "attributes": []
            },
            "title": {
              "name": "title",
              "isArray": false,
              "type": "String",
              "isRequired": true,
              "attributes": []
            },
            "dueDate": {
              "name": "dueDate",
              "isArray": false,
              "type": "AWSDate",
              "isRequired": true,
              "attributes": []
            },
            "level": {
              "name": "level",
              "isArray": false,
              "type": "String",
              "isRequired": true,
              "attributes": []
            },
            "status": {
              "name": "status",
              "isArray": false,
              "type": {
                "enum": "AssignmentStatus"
              },
              "isRequired": true,
              "attributes": []
            },
            "requiredWords": {
              "name": "requiredWords",
              "isArray": true,
              "type": "String",
              "isRequired": false,
              "attributes": [],
              "isArrayNullable": true
            },
            "excludedWords": {
              "name": "excludedWords",
              "isArray": true,
              "type": "String",
              "isRequired": false,
              "attributes": [],
              "isArrayNullable": true
            },
            "createdAt": {
              "name": "createdAt",
              "isArray": false,
              "type": "AWSDateTime",
              "isRequired": true,
              "attributes": []
            },
            "updatedAt": {
              "name": "updatedAt",
              "isArray": false,
              "type": "AWSDateTime",
              "isRequired": true,
              "attributes": []
            }
          }
        },
        "SubmissionSummaryView": {
          "name": "SubmissionSummaryView",
          "fields": {
            "id": {
              "name": "id",
              "isArray": false,
              "type": "ID",
              "isRequired": true,
              "attributes": []
            },
            "assignmentId": {
              "name": "assignmentId",
              "isArray": false,
              "type": "ID",
              "isRequired": true,
              "attributes": []
            },
            "teacherId": {
              "name": "teacherId",
              "isArray": false,
              "type": "ID",
              "isRequired": true,
              "attributes": []
            },
            "studentId": {
              "name": "studentId",
              "isArray": false,
              "type": "ID",
              "isRequired": true,
              "attributes": []
            },
            "studentName": {
              "name": "studentName",
              "isArray": false,
              "type": "String",
              "isRequired": true,
              "attributes": []
            },
            "submittedAt": {
              "name": "submittedAt",
              "isArray": false,
              "type": "AWSDateTime",
              "isRequired": true,
              "attributes": []
            },
            "score": {
              "name": "score",
              "isArray": false,
              "type": "Int",
              "isRequired": false,
              "attributes": []
            },
            "unknownWords": {
              "name": "unknownWords",
              "isArray": true,
              "type": "String",
              "isRequired": false,
              "attributes": [],
              "isArrayNullable": true
            },
            "createdAt": {
              "name": "createdAt",
              "isArray": false,
              "type": "AWSDateTime",
              "isRequired": true,
              "attributes": []
            },
            "updatedAt": {
              "name": "updatedAt",
              "isArray": false,
              "type": "AWSDateTime",
              "isRequired": true,
              "attributes": []
            }
          }
        },
        "ClassSummaryView": {
          "name": "ClassSummaryView",
          "fields": {
            "id": {
              "name": "id",
              "isArray": false,
              "type": "ID",
              "isRequired": true,
              "attributes": []
            },
            "teacherId": {
              "name": "teacherId",
              "isArray": false,
              "type": "ID",
              "isRequired": true,
              "attributes": []
            },
            "name": {
              "name": "name",
              "isArray": false,
              "type": "String",
              "isRequired": true,
              "attributes": []
            },
            "studentCount": {
              "name": "studentCount",
              "isArray": false,
              "type": "Int",
              "isRequired": true,
              "attributes": []
            },
            "averageLevel": {
              "name": "averageLevel",
              "isArray": false,
              "type": "String",
              "isRequired": true,
              "attributes": []
            },
            "completionRate": {
              "name": "completionRate",
              "isArray": false,
              "type": "Float",
              "isRequired": true,
              "attributes": []
            },
            "mostChallengingWord": {
              "name": "mostChallengingWord",
              "isArray": false,
              "type": "String",
              "isRequired": false,
              "attributes": []
            },
            "createdAt": {
              "name": "createdAt",
              "isArray": false,
              "type": "AWSDateTime",
              "isRequired": true,
              "attributes": []
            },
            "updatedAt": {
              "name": "updatedAt",
              "isArray": false,
              "type": "AWSDateTime",
              "isRequired": true,
              "attributes": []
            }
          }
        },
        "StoryConnection": {
          "name": "StoryConnection",
          "fields": {
            "items": {
              "name": "items",
              "isArray": true,
              "type": {
                "nonModel": "StoryView"
              },
              "isRequired": false,
              "attributes": [],
              "isArrayNullable": true
            },
            "nextToken": {
              "name": "nextToken",
              "isArray": false,
              "type": "String",
              "isRequired": false,
              "attributes": []
            }
          }
        },
        "StudentDashboardPayload": {
          "name": "StudentDashboardPayload",
          "fields": {
            "profile": {
              "name": "profile",
              "isArray": false,
              "type": {
                "nonModel": "StudentProfileView"
              },
              "isRequired": false,
              "attributes": []
            },
            "recommendations": {
              "name": "recommendations",
              "isArray": true,
              "type": {
                "nonModel": "StoryView"
              },
              "isRequired": false,
              "attributes": [],
              "isArrayNullable": true
            }
          }
        },
        "TeacherDashboardPayload": {
          "name": "TeacherDashboardPayload",
          "fields": {
            "profile": {
              "name": "profile",
              "isArray": false,
              "type": {
                "nonModel": "TeacherProfileView"
              },
              "isRequired": false,
              "attributes": []
            },
            "assignments": {
              "name": "assignments",
              "isArray": true,
              "type": {
                "nonModel": "AssignmentView"
              },
              "isRequired": false,
              "attributes": [],
              "isArrayNullable": true
            },
            "submissions": {
              "name": "submissions",
              "isArray": true,
              "type": {
                "nonModel": "SubmissionSummaryView"
              },
              "isRequired": false,
              "attributes": [],
              "isArrayNullable": true
            },
            "classes": {
              "name": "classes",
              "isArray": true,
              "type": {
                "nonModel": "ClassSummaryView"
              },
              "isRequired": false,
              "attributes": [],
              "isArrayNullable": true
            }
          }
        },
        "StoryGenerationPayload": {
          "name": "StoryGenerationPayload",
          "fields": {
            "story": {
              "name": "story",
              "isArray": false,
              "type": {
                "nonModel": "StoryView"
              },
              "isRequired": false,
              "attributes": []
            },
            "newWords": {
              "name": "newWords",
              "isArray": true,
              "type": {
                "nonModel": "WordView"
              },
              "isRequired": false,
              "attributes": [],
              "isArrayNullable": true
            }
          }
        }
      },
      "queries": {
        "getStudentDashboard": {
          "name": "getStudentDashboard",
          "isArray": false,
          "type": {
            "nonModel": "StudentDashboardPayload"
          },
          "isRequired": false,
          "arguments": {
            "id": {
              "name": "id",
              "isArray": false,
              "type": "ID",
              "isRequired": false
            }
          }
        },
        "getTeacherDashboard": {
          "name": "getTeacherDashboard",
          "isArray": false,
          "type": {
            "nonModel": "TeacherDashboardPayload"
          },
          "isRequired": false,
          "arguments": {
            "id": {
              "name": "id",
              "isArray": false,
              "type": "ID",
              "isRequired": false
            }
          }
        },
        "listStudentStories": {
          "name": "listStudentStories",
          "isArray": false,
          "type": {
            "nonModel": "StoryConnection"
          },
          "isRequired": false,
          "arguments": {
            "studentId": {
              "name": "studentId",
              "isArray": false,
              "type": "ID",
              "isRequired": false
            },
            "limit": {
              "name": "limit",
              "isArray": false,
              "type": "Int",
              "isRequired": false
            },
            "nextToken": {
              "name": "nextToken",
              "isArray": false,
              "type": "String",
              "isRequired": false
            }
          }
        },
        "listTeacherAssignments": {
          "name": "listTeacherAssignments",
          "isArray": true,
          "type": {
            "nonModel": "AssignmentView"
          },
          "isRequired": false,
          "isArrayNullable": true,
          "arguments": {
            "teacherId": {
              "name": "teacherId",
              "isArray": false,
              "type": "ID",
              "isRequired": false
            }
          }
        }
      },
      "mutations": {
        "generateStory": {
          "name": "generateStory",
          "isArray": false,
          "type": {
            "nonModel": "StoryGenerationPayload"
          },
          "isRequired": false,
          "arguments": {
            "level": {
              "name": "level",
              "isArray": false,
              "type": "String",
              "isRequired": true
            },
            "age": {
              "name": "age",
              "isArray": false,
              "type": "Int",
              "isRequired": true
            },
            "knownWords": {
              "name": "knownWords",
              "isArray": true,
              "type": "String",
              "isRequired": false,
              "isArrayNullable": false
            },
            "unknownWords": {
              "name": "unknownWords",
              "isArray": true,
              "type": "String",
              "isRequired": false,
              "isArrayNullable": false
            },
            "requiredWords": {
              "name": "requiredWords",
              "isArray": true,
              "type": "String",
              "isRequired": false,
              "isArrayNullable": true
            },
            "excludedWords": {
              "name": "excludedWords",
              "isArray": true,
              "type": "String",
              "isRequired": false,
              "isArrayNullable": true
            },
            "mode": {
              "name": "mode",
              "isArray": false,
              "type": {
                "enum": "StoryGenerationMode"
              },
              "isRequired": true
            }
          }
        },
        "updateWordMastery": {
          "name": "updateWordMastery",
          "isArray": false,
          "type": {
            "model": "Word"
          },
          "isRequired": false,
          "arguments": {
            "studentId": {
              "name": "studentId",
              "isArray": false,
              "type": "ID",
              "isRequired": true
            },
            "wordId": {
              "name": "wordId",
              "isArray": false,
              "type": "ID",
              "isRequired": true
            },
            "mastery": {
              "name": "mastery",
              "isArray": false,
              "type": {
                "enum": "WordMastery"
              },
              "isRequired": true
            }
          }
        },
        "createTeacherAssignment": {
          "name": "createTeacherAssignment",
          "isArray": false,
          "type": {
            "model": "Assignment"
          },
          "isRequired": false,
          "arguments": {
            "teacherId": {
              "name": "teacherId",
              "isArray": false,
              "type": "ID",
              "isRequired": true
            },
            "title": {
              "name": "title",
              "isArray": false,
              "type": "String",
              "isRequired": true
            },
            "dueDate": {
              "name": "dueDate",
              "isArray": false,
              "type": "AWSDate",
              "isRequired": true
            },
            "level": {
              "name": "level",
              "isArray": false,
              "type": "String",
              "isRequired": true
            },
            "requiredWords": {
              "name": "requiredWords",
              "isArray": true,
              "type": "String",
              "isRequired": false,
              "isArrayNullable": true
            },
            "excludedWords": {
              "name": "excludedWords",
              "isArray": true,
              "type": "String",
              "isRequired": false,
              "isArrayNullable": true
            }
          }
        }
      }
    }
  },
  "version": "1.4"
}